JiqiZhixin2019GaofenJiaochengRumenJiehuo/README.md
JiqiZhixin2019GaofenJiaochengRumenJiehuo/__init__.py
JiqiZhixin2019GaofenJiaochengRumenJiehuo/__main__.py
JiqiZhixin2019GaofenJiaochengRumenJiehuo/file.epub
JiqiZhixin2019GaofenJiaochengRumenJiehuo/index.html
JiqiZhixin2019GaofenJiaochengRumenJiehuo/css/__init__.py
JiqiZhixin2019GaofenJiaochengRumenJiehuo/css/annotations.css
JiqiZhixin2019GaofenJiaochengRumenJiehuo/css/main.css
JiqiZhixin2019GaofenJiaochengRumenJiehuo/css/normalize.css
JiqiZhixin2019GaofenJiaochengRumenJiehuo/css/popup.css
JiqiZhixin2019GaofenJiaochengRumenJiehuo/font/__init__.py
JiqiZhixin2019GaofenJiaochengRumenJiehuo/font/fontello.eot
JiqiZhixin2019GaofenJiaochengRumenJiehuo/font/fontello.svg
JiqiZhixin2019GaofenJiaochengRumenJiehuo/font/fontello.ttf
JiqiZhixin2019GaofenJiaochengRumenJiehuo/font/fontello.woff
JiqiZhixin2019GaofenJiaochengRumenJiehuo/img/__init__.py
JiqiZhixin2019GaofenJiaochengRumenJiehuo/img/annotator-glyph-sprite.png
JiqiZhixin2019GaofenJiaochengRumenJiehuo/img/annotator-icon-sprite.png
JiqiZhixin2019GaofenJiaochengRumenJiehuo/img/apple-touch-icon.png
JiqiZhixin2019GaofenJiaochengRumenJiehuo/img/cancelfullscreen.png
JiqiZhixin2019GaofenJiaochengRumenJiehuo/img/close.png
JiqiZhixin2019GaofenJiaochengRumenJiehuo/img/fullscreen.png
JiqiZhixin2019GaofenJiaochengRumenJiehuo/img/loader.gif
JiqiZhixin2019GaofenJiaochengRumenJiehuo/img/menu-icon.png
JiqiZhixin2019GaofenJiaochengRumenJiehuo/img/save.png
JiqiZhixin2019GaofenJiaochengRumenJiehuo/img/saved.png
JiqiZhixin2019GaofenJiaochengRumenJiehuo/img/settings-s.png
JiqiZhixin2019GaofenJiaochengRumenJiehuo/img/settings.png
JiqiZhixin2019GaofenJiaochengRumenJiehuo/img/star.png
JiqiZhixin2019GaofenJiaochengRumenJiehuo/js/__init__.py
JiqiZhixin2019GaofenJiaochengRumenJiehuo/js/epub.js
JiqiZhixin2019GaofenJiaochengRumenJiehuo/js/epub.min.js
JiqiZhixin2019GaofenJiaochengRumenJiehuo/js/epub.min.map
JiqiZhixin2019GaofenJiaochengRumenJiehuo/js/hooks.min.js
jiqi_zhixin_2019_gaofen_jiaocheng_rumen_jiehuo-2024.3.5.0.dist-info/METADATA
jiqi_zhixin_2019_gaofen_jiaocheng_rumen_jiehuo-2024.3.5.0.dist-info/WHEEL
jiqi_zhixin_2019_gaofen_jiaocheng_rumen_jiehuo-2024.3.5.0.dist-info/entry_points.txt
jiqi_zhixin_2019_gaofen_jiaocheng_rumen_jiehuo-2024.3.5.0.dist-info/top_level.txt
jiqi_zhixin_2019_gaofen_jiaocheng_rumen_jiehuo-2024.3.5.0.dist-info/RECORD
